messages.py
pure_pcapy.py
tabulate.py
event_bus_utils/__init__.py
event_bus_utils/event_bus_utils.py
event_bus_utils/packet_dumper.py
event_bus_utils/rmq_handler.py
ioppytest_cli/__init__.py
ioppytest_cli/__main__.py
ioppytest_cli/ioppytest_cli.py
ioppytest_utils-1.2.14.dist-info/METADATA
ioppytest_utils-1.2.14.dist-info/RECORD
ioppytest_utils-1.2.14.dist-info/WHEEL
ioppytest_utils-1.2.14.dist-info/entry_points.txt
ioppytest_utils-1.2.14.dist-info/top_level.txt
