Metadata-Version: 2.1
Name: ioppytest-utils
Version: 1.2.14
Summary: Set of useful packages, modules  and programs for ioppytest components.Installs `ioppytest-cli` Command line interface for interacting with ioppytest testing tool (all interactions happen over AMQP event bus).
Home-page: https://gitlab.f-interop.eu/f-interop-contributors/utils
Author: Federico Sismondi
Author-email: federicosismondi@gmail.com
Maintainer: Federico Sismondi
Maintainer-email: federicosismondi@gmail.com
License: GPLv3+
Platform: UNKNOWN
Classifier: Development Status :: 3 - Alpha
Classifier: Intended Audience :: Science/Research
Classifier: Intended Audience :: Developers
Classifier: Programming Language :: Python
Classifier: Programming Language :: Python :: 3
Classifier: Programming Language :: Python :: 3.5
Classifier: Programming Language :: Python :: 3.6
Classifier: Topic :: Internet
Classifier: Topic :: Software Development :: Testing
Classifier: Topic :: Scientific/Engineering
Classifier: Operating System :: POSIX
Classifier: Operating System :: Unix
Classifier: Operating System :: MacOS
Requires-Dist: click (==6.7)
Requires-Dist: click-repl (==0.1.2)
Requires-Dist: pika (==0.11.0)
Requires-Dist: prompt-toolkit (==1.0.15)
Requires-Dist: wcwidth (==0.1.7)
